moana/__about__.py
moana/__init__.py
moana/_version.py
moana/estimators.py
moana/frames.py
moana/lens.py
moana/lookup.py
moana/corner/LICENSE
moana/corner/__init__.py
moana/corner/tools.py
moana/dbc/__init__.py
moana/dbc/instruments.py
moana/dbc/io.py
moana/dbc/tools.py
moana/stylelib/__init__.py
moana/stylelib/corner_plots_times.mplstyle
moana_pypi-0.2.0.1.dist-info/METADATA
moana_pypi-0.2.0.1.dist-info/WHEEL
moana_pypi-0.2.0.1.dist-info/licenses/AUTHORS.rst
moana_pypi-0.2.0.1.dist-info/licenses/LICENSE
moana_pypi-0.2.0.1.dist-info/RECORD
