Metadata-Version: 2.4
Name: moana-pypi
Version: 0.2.0.1
Summary: MOAna: Microlensing Observations ANAlysis tools
Project-URL: Homepage, https://github.com/clementranc/moana
Author: Clément Ranc, Stela IS, Stela IS, MOAna authors
Author-email: ranc@iap.fr
License-Expression: MIT
License-File: AUTHORS.rst
License-File: LICENSE
Requires-Python: >=3.11
Requires-Dist: matplotlib
Requires-Dist: pandas
Requires-Dist: scipy
